djinntoux/__init__.py
djinntoux/abstract_models.py
djinntoux/context_processors.py
djinntoux/middleware.py
djinntoux/rename.py
djinntoux/settings2.py
djinntoux/urls2.py
djinntoux/utils/scrape.py
djinntoux-0.0.8.19.dist-info/METADATA
djinntoux-0.0.8.19.dist-info/WHEEL
djinntoux-0.0.8.19.dist-info/licenses/LICENSE
djinntoux-0.0.8.19.dist-info/RECORD
