Metadata-Version: 2.4
Name: djinntoux
Version: 0.0.8.19
Summary: Generic reusable bits for Django projects
Project-URL: Repository, https://github.com/venteto/djinntoux
License-Expression: MIT
License-File: LICENSE
Requires-Python: >=3.13
Requires-Dist: beautifulsoup4>=4.13.3
Requires-Dist: django-environ>=0.12.0
Requires-Dist: django-htmlmin>=0.11.0
Requires-Dist: django-tree-queries>=0.19.0
Requires-Dist: django>=5.2a1
Requires-Dist: djangoql>=0.18.1
Requires-Dist: gunicorn>=23.0.0
Requires-Dist: pip-autoremove>=0.10.0
Requires-Dist: psycopg>=3.2.4
Requires-Dist: requests>=2.32.3
Requires-Dist: uuid6>=2024.7.10
